highbalance/__init__.py
highbalance-0.0.5.dist-info/LICENSE
highbalance-0.0.5.dist-info/METADATA
highbalance-0.0.5.dist-info/WHEEL
highbalance-0.0.5.dist-info/top_level.txt
highbalance-0.0.5.dist-info/RECORD
