Metadata-Version: 2.1
Name: highbalance
Version: 0.0.5
Summary: discord bot lover
Author: 7sosas
Author-email: tynopehehe@gmail.com
Keywords: arithmetic,math,mathematics,python tutorial,highbalance upadhyay
Classifier: Development Status :: 1 - Planning
Classifier: Intended Audience :: Developers
Classifier: Programming Language :: Python :: 3
Classifier: Operating System :: Unix
Classifier: Operating System :: MacOS :: MacOS X
Classifier: Operating System :: Microsoft :: Windows
License-File: LICENSE
